collectionz/__init__.py
collectionz/collectionz.py
collectionz/tests.py
collectionz-0.0.1.dist-info/DESCRIPTION.rst
collectionz-0.0.1.dist-info/METADATA
collectionz-0.0.1.dist-info/RECORD
collectionz-0.0.1.dist-info/WHEEL
collectionz-0.0.1.dist-info/metadata.json
collectionz-0.0.1.dist-info/top_level.txt
