Metadata-Version: 2.0
Name: collectionz
Version: 0.0.1
Summary: A set of utility data structures that could fit in the ``collections`` package of Python's standard library.
Home-page: https://github.com/manugrandio/collectionz
Author: Manu Grandío Bravo
Author-email: manugrandio@fastmail.fm
License: BSD
Keywords: utility collections
Platform: UNKNOWN
Classifier: Development Status :: 3 - Alpha
Classifier: License :: OSI Approved :: BSD License
Classifier: Programming Language :: Python
Classifier: Programming Language :: Python :: 3
Classifier: Programming Language :: Python :: Implementation :: CPython
